niconico/__init__.py
niconico/__main__.py
niconico/base/__init__.py
niconico/base/client.py
niconico/channel/__init__.py
niconico/channel/search.py
niconico/decorators.py
niconico/exceptions.py
niconico/niconico.py
niconico/objects/__init__.py
niconico/objects/channel/__init__.py
niconico/objects/channel/search.py
niconico/objects/common.py
niconico/objects/nvapi.py
niconico/objects/user/__init__.py
niconico/objects/user/search.py
niconico/objects/video/__init__.py
niconico/objects/video/ranking.py
niconico/objects/video/search.py
niconico/objects/video/watch.py
niconico/py.typed
niconico/user/__init__.py
niconico/user/search.py
niconico/utils.py
niconico/video/__init__.py
niconico/video/ranking.py
niconico/video/search.py
niconico/video/watch.py
niconico_py-2.1.0.dist-info/LICENSE
niconico_py-2.1.0.dist-info/METADATA
niconico_py-2.1.0.dist-info/WHEEL
niconico_py-2.1.0.dist-info/entry_points.txt
niconico_py-2.1.0.dist-info/RECORD
