Metadata-Version: 2.1
Name: niconico.py
Version: 2.1.0
Summary: API wrapper for NicoNico services
Home-page: https://github.com/niconicolibs/niconico.py
License: MIT
Author: Negima1072
Author-email: ngm1072@gmail.com
Requires-Python: >=3.8
Classifier: License :: OSI Approved :: MIT License
Classifier: Programming Language :: Python :: 3
Classifier: Programming Language :: Python :: 3.8
Classifier: Programming Language :: Python :: 3.9
Classifier: Programming Language :: Python :: 3.10
Classifier: Programming Language :: Python :: 3.11
Classifier: Programming Language :: Python :: 3.12
Requires-Dist: pydantic (>=2.8.2,<3.0.0)
Requires-Dist: requests (>=2.32.3,<3.0.0)
Project-URL: Repository, https://github.com/niconicolibs/niconico.py
